pydebcontents/__init__.py
pydebcontents/_contents_dict.py
pydebcontents/_contents_file.py
pydebcontents/cli.py
pydebcontents/py.typed
pydebcontents/test/__init__.py
pydebcontents/test/conftest.py
pydebcontents/test/test_contents_dict.py
pydebcontents/test/test_contents_file.py
pydebcontents-0.3.1.dist-info/LICENSE
pydebcontents-0.3.1.dist-info/METADATA
pydebcontents-0.3.1.dist-info/WHEEL
pydebcontents-0.3.1.dist-info/entry_points.txt
pydebcontents-0.3.1.dist-info/top_level.txt
pydebcontents-0.3.1.dist-info/RECORD
