Metadata-Version: 2.1
Name: pydebcontents
Version: 0.3.1
Summary: Utilities working with Debian repository Contents files
Author-email: Stuart Prescott <stuart@debian.org>
License: BSD-3-Clause
Project-URL: homepage, https://salsa.debian.org/debian-irc-team/pydebcontents/
Keywords: debian,package,contents,archive
Requires-Python: >=3.7
License-File: LICENSE
Provides-Extra: test
Requires-Dist: pytest ; extra == 'test'
Requires-Dist: pytest-cov ; extra == 'test'
Requires-Dist: requests ; extra == 'test'
